LICENSE
README.md
setup.py
falcon_easy_crud/__init__.py
falcon_easy_crud.egg-info/PKG-INFO
falcon_easy_crud.egg-info/SOURCES.txt
falcon_easy_crud.egg-info/dependency_links.txt
falcon_easy_crud.egg-info/requires.txt
falcon_easy_crud.egg-info/top_level.txt